<?xml version="1.0" encoding="UTF-8"?>
<!--
Created with Funkin Packer v0.1.3 https://neeeoo.github.io/funkin-packer/
-->
<TextureAtlas imagePath="Yourself_BF_Assets.png" width="8160" height="3750">
	<SubTexture name="BFDown0000" x="3882" y="674" width="718" height="705" rotated="true" frameX="-0" frameY="-23" frameWidth="705" frameHeight="742"/>
	<SubTexture name="BFDown0001" x="3158" y="672" width="724" height="701" rotated="true" frameX="-2" frameY="-18" frameWidth="705" frameHeight="742"/>
	<SubTexture name="BFDown0002" x="3158" y="672" width="724" height="701" rotated="true" frameX="-2" frameY="-18" frameWidth="705" frameHeight="742"/>
	<SubTexture name="BFDown0003" x="5793" y="0" width="737" height="682" rotated="true" frameX="-12" frameY="-4" frameWidth="705" frameHeight="742"/>
	<SubTexture name="BFDown0004" x="5793" y="0" width="737" height="682" rotated="true" frameX="-12" frameY="-4" frameWidth="705" frameHeight="742"/>
	<SubTexture name="BFDown0005" x="5054" y="0" width="739" height="676" rotated="true" frameX="-15" frameY="-2" frameWidth="705" frameHeight="742"/>
	<SubTexture name="BFDown0006" x="5054" y="0" width="739" height="676" rotated="true" frameX="-15" frameY="-2" frameWidth="705" frameHeight="742"/>
	<SubTexture name="BFDown0007" x="5054" y="0" width="739" height="676" rotated="true" frameX="-15" frameY="-2" frameWidth="705" frameHeight="742"/>
	<SubTexture name="BFDown0008" x="4313" y="0" width="741" height="674" rotated="true" frameX="-16" frameY="-0" frameWidth="705" frameHeight="742"/>
	<SubTexture name="BFDown0009" x="4313" y="0" width="741" height="674" rotated="true" frameX="-16" frameY="-0" frameWidth="705" frameHeight="742"/>
	<SubTexture name="BFDown0010" x="4313" y="0" width="741" height="674" rotated="true" frameX="-16" frameY="-0" frameWidth="705" frameHeight="742"/>
	<SubTexture name="BFDown0011" x="4313" y="0" width="741" height="674" rotated="true" frameX="-16" frameY="-0" frameWidth="705" frameHeight="742"/>
	<SubTexture name="BFDown0012" x="4313" y="0" width="741" height="674" rotated="true" frameX="-16" frameY="-0" frameWidth="705" frameHeight="742"/>
	<SubTexture name="BFDown0013" x="4313" y="0" width="741" height="674" rotated="true" frameX="-16" frameY="-0" frameWidth="705" frameHeight="742"/>
	<SubTexture name="BFDownALT0000" x="4447" y="2900" width="930" height="850" rotated="true" frameX="-0" frameY="-6" frameWidth="850" frameHeight="937"/>
	<SubTexture name="BFDownALT0001" x="3511" y="2893" width="936" height="840" rotated="true" frameX="-8" frameY="-0" frameWidth="850" frameHeight="937"/>
	<SubTexture name="BFDownALT0002" x="3511" y="2893" width="936" height="840" rotated="true" frameX="-8" frameY="-0" frameWidth="850" frameHeight="937"/>
	<SubTexture name="BFDownALT0003" x="2581" y="2883" width="930" height="817" rotated="true" frameX="-22" frameY="-6" frameWidth="850" frameHeight="937"/>
	<SubTexture name="BFDownALT0004" x="2581" y="2883" width="930" height="817" rotated="true" frameX="-22" frameY="-6" frameWidth="850" frameHeight="937"/>
	<SubTexture name="BFDownALT0005" x="771" y="2865" width="907" height="807" rotated="true" frameX="-29" frameY="-29" frameWidth="850" frameHeight="937"/>
	<SubTexture name="BFDownALT0006" x="771" y="2865" width="907" height="807" rotated="true" frameX="-29" frameY="-29" frameWidth="850" frameHeight="937"/>
	<SubTexture name="BFDownALT0007" x="771" y="2865" width="907" height="807" rotated="true" frameX="-29" frameY="-29" frameWidth="850" frameHeight="937"/>
	<SubTexture name="BFDownALT0008" x="1678" y="2874" width="903" height="809" rotated="true" frameX="-26" frameY="-33" frameWidth="850" frameHeight="937"/>
	<SubTexture name="BFDownALT0009" x="1678" y="2874" width="903" height="809" rotated="true" frameX="-26" frameY="-33" frameWidth="850" frameHeight="937"/>
	<SubTexture name="BFDownALT0010" x="1678" y="2874" width="903" height="809" rotated="true" frameX="-26" frameY="-33" frameWidth="850" frameHeight="937"/>
	<SubTexture name="BFDownALT0011" x="1678" y="2874" width="903" height="809" rotated="true" frameX="-26" frameY="-33" frameWidth="850" frameHeight="937"/>
	<SubTexture name="BFDownALT0012" x="1678" y="2874" width="903" height="809" rotated="true" frameX="-26" frameY="-33" frameWidth="850" frameHeight="937"/>
	<SubTexture name="BFDownALT0013" x="1678" y="2874" width="903" height="809" rotated="true" frameX="-26" frameY="-33" frameWidth="850" frameHeight="937"/>
	<SubTexture name="BFIdle0000" x="801" y="648" width="782" height="694" rotated="true" frameX="-8" frameY="-23" frameWidth="702" frameHeight="805"/>
	<SubTexture name="BFIdle0001" x="1583" y="666" width="783" height="694" rotated="true" frameX="-4" frameY="-22" frameWidth="702" frameHeight="805"/>
	<SubTexture name="BFIdle0002" x="1583" y="666" width="783" height="694" rotated="true" frameX="-4" frameY="-22" frameWidth="702" frameHeight="805"/>
	<SubTexture name="BFIdle0003" x="2366" y="672" width="792" height="695" rotated="true" frameX="-0" frameY="-13" frameWidth="702" frameHeight="805"/>
	<SubTexture name="BFIdle0004" x="2366" y="672" width="792" height="695" rotated="true" frameX="-0" frameY="-13" frameWidth="702" frameHeight="805"/>
	<SubTexture name="BFIdle0005" x="0" y="641" width="801" height="690" rotated="true" frameX="-5" frameY="-4" frameWidth="702" frameHeight="805"/>
	<SubTexture name="BFIdle0006" x="0" y="641" width="801" height="690" rotated="true" frameX="-5" frameY="-4" frameWidth="702" frameHeight="805"/>
	<SubTexture name="BFIdle0007" x="0" y="641" width="801" height="690" rotated="true" frameX="-5" frameY="-4" frameWidth="702" frameHeight="805"/>
	<SubTexture name="BFIdle0008" x="6530" y="0" width="805" height="685" rotated="true" frameX="-9" frameY="-0" frameWidth="702" frameHeight="805"/>
	<SubTexture name="BFIdle0009" x="6530" y="0" width="805" height="685" rotated="true" frameX="-9" frameY="-0" frameWidth="702" frameHeight="805"/>
	<SubTexture name="BFIdle0010" x="6530" y="0" width="805" height="685" rotated="true" frameX="-9" frameY="-0" frameWidth="702" frameHeight="805"/>
	<SubTexture name="BFIdle0011" x="6530" y="0" width="805" height="685" rotated="true" frameX="-9" frameY="-0" frameWidth="702" frameHeight="805"/>
	<SubTexture name="BFIdle0012" x="7335" y="0" width="805" height="686" rotated="true" frameX="-9" frameY="-0" frameWidth="702" frameHeight="805"/>
	<SubTexture name="BFIdle0013" x="7335" y="0" width="805" height="686" rotated="true" frameX="-9" frameY="-0" frameWidth="702" frameHeight="805"/>
	<SubTexture name="BFIdle0014" x="7335" y="0" width="805" height="686" rotated="true" frameX="-9" frameY="-0" frameWidth="702" frameHeight="805"/>
	<SubTexture name="BFLeft0000" x="3984" y="2133" width="801" height="760" rotated="true" frameX="-0" frameY="-0" frameWidth="772" frameHeight="801"/>
	<SubTexture name="BFLeft0001" x="3193" y="2124" width="791" height="759" rotated="true" frameX="-4" frameY="-10" frameWidth="772" frameHeight="801"/>
	<SubTexture name="BFLeft0002" x="3193" y="2124" width="791" height="759" rotated="true" frameX="-4" frameY="-10" frameWidth="772" frameHeight="801"/>
	<SubTexture name="BFLeft0003" x="796" y="1342" width="787" height="752" rotated="true" frameX="-18" frameY="-14" frameWidth="772" frameHeight="801"/>
	<SubTexture name="BFLeft0004" x="796" y="1342" width="787" height="752" rotated="true" frameX="-18" frameY="-14" frameWidth="772" frameHeight="801"/>
	<SubTexture name="BFLeft0005" x="0" y="1331" width="796" height="742" rotated="true" frameX="-30" frameY="-5" frameWidth="772" frameHeight="801"/>
	<SubTexture name="BFLeft0006" x="0" y="1331" width="796" height="742" rotated="true" frameX="-30" frameY="-5" frameWidth="772" frameHeight="801"/>
	<SubTexture name="BFLeft0007" x="0" y="1331" width="796" height="742" rotated="true" frameX="-30" frameY="-5" frameWidth="772" frameHeight="801"/>
	<SubTexture name="BFLeft0008" x="7022" y="686" width="797" height="740" rotated="true" frameX="-32" frameY="-4" frameWidth="772" frameHeight="801"/>
	<SubTexture name="BFLeft0009" x="7022" y="686" width="797" height="740" rotated="true" frameX="-32" frameY="-4" frameWidth="772" frameHeight="801"/>
	<SubTexture name="BFLeft0010" x="7022" y="686" width="797" height="740" rotated="true" frameX="-32" frameY="-4" frameWidth="772" frameHeight="801"/>
	<SubTexture name="BFLeft0011" x="7022" y="686" width="797" height="740" rotated="true" frameX="-32" frameY="-4" frameWidth="772" frameHeight="801"/>
	<SubTexture name="BFLeft0012" x="7022" y="686" width="797" height="740" rotated="true" frameX="-32" frameY="-4" frameWidth="772" frameHeight="801"/>
	<SubTexture name="BFLeft0013" x="7022" y="686" width="797" height="740" rotated="true" frameX="-32" frameY="-4" frameWidth="772" frameHeight="801"/>
	<SubTexture name="BFLeft0014" x="7022" y="686" width="797" height="740" rotated="true" frameX="-32" frameY="-4" frameWidth="772" frameHeight="801"/>
	<SubTexture name="BFLeftALT0000" x="4785" y="2140" width="801" height="760" rotated="true" frameX="-0" frameY="-0" frameWidth="788" frameHeight="801"/>
	<SubTexture name="BFLeftALT0001" x="1593" y="2107" width="791" height="758" rotated="true" frameX="-4" frameY="-10" frameWidth="788" frameHeight="801"/>
	<SubTexture name="BFLeftALT0002" x="1593" y="2107" width="791" height="758" rotated="true" frameX="-4" frameY="-10" frameWidth="788" frameHeight="801"/>
	<SubTexture name="BFLeftALT0003" x="7373" y="1426" width="787" height="752" rotated="true" frameX="-18" frameY="-14" frameWidth="788" frameHeight="801"/>
	<SubTexture name="BFLeftALT0004" x="7373" y="1426" width="787" height="752" rotated="true" frameX="-18" frameY="-14" frameWidth="788" frameHeight="801"/>
	<SubTexture name="BFLeftALT0005" x="0" y="2073" width="796" height="754" rotated="true" frameX="-30" frameY="-5" frameWidth="788" frameHeight="801"/>
	<SubTexture name="BFLeftALT0006" x="0" y="2073" width="796" height="754" rotated="true" frameX="-30" frameY="-5" frameWidth="788" frameHeight="801"/>
	<SubTexture name="BFLeftALT0007" x="0" y="2073" width="796" height="754" rotated="true" frameX="-30" frameY="-5" frameWidth="788" frameHeight="801"/>
	<SubTexture name="BFLeftALT0008" x="796" y="2107" width="797" height="756" rotated="true" frameX="-32" frameY="-4" frameWidth="788" frameHeight="801"/>
	<SubTexture name="BFLeftALT0009" x="796" y="2107" width="797" height="756" rotated="true" frameX="-32" frameY="-4" frameWidth="788" frameHeight="801"/>
	<SubTexture name="BFLeftALT0010" x="796" y="2107" width="797" height="756" rotated="true" frameX="-32" frameY="-4" frameWidth="788" frameHeight="801"/>
	<SubTexture name="BFLeftALT0011" x="796" y="2107" width="797" height="756" rotated="true" frameX="-32" frameY="-4" frameWidth="788" frameHeight="801"/>
	<SubTexture name="BFLeftALT0012" x="796" y="2107" width="797" height="756" rotated="true" frameX="-32" frameY="-4" frameWidth="788" frameHeight="801"/>
	<SubTexture name="BFLeftALT0013" x="796" y="2107" width="797" height="756" rotated="true" frameX="-32" frameY="-4" frameWidth="788" frameHeight="801"/>
	<SubTexture name="BFLeftALT0014" x="796" y="2107" width="797" height="756" rotated="true" frameX="-32" frameY="-4" frameWidth="788" frameHeight="801"/>
	<SubTexture name="BFRight0000" x="2389" y="1373" width="807" height="745" rotated="true" frameX="-9" frameY="-2" frameWidth="754" frameHeight="809"/>
	<SubTexture name="BFRight0001" x="3196" y="1379" width="804" height="745" rotated="true" frameX="-6" frameY="-5" frameWidth="754" frameHeight="809"/>
	<SubTexture name="BFRight0002" x="3196" y="1379" width="804" height="745" rotated="true" frameX="-6" frameY="-5" frameWidth="754" frameHeight="809"/>
	<SubTexture name="BFRight0003" x="6213" y="685" width="809" height="718" rotated="true" frameX="-2" frameY="-0" frameWidth="754" frameHeight="809"/>
	<SubTexture name="BFRight0004" x="6213" y="685" width="809" height="718" rotated="true" frameX="-2" frameY="-0" frameWidth="754" frameHeight="809"/>
	<SubTexture name="BFRight0005" x="5406" y="682" width="807" height="713" rotated="true" frameX="-0" frameY="-2" frameWidth="754" frameHeight="809"/>
	<SubTexture name="BFRight0006" x="5406" y="682" width="807" height="713" rotated="true" frameX="-0" frameY="-2" frameWidth="754" frameHeight="809"/>
	<SubTexture name="BFRight0007" x="5406" y="682" width="807" height="713" rotated="true" frameX="-0" frameY="-2" frameWidth="754" frameHeight="809"/>
	<SubTexture name="BFRight0008" x="4600" y="676" width="806" height="712" rotated="true" frameX="-0" frameY="-3" frameWidth="754" frameHeight="809"/>
	<SubTexture name="BFRight0009" x="4600" y="676" width="806" height="712" rotated="true" frameX="-0" frameY="-3" frameWidth="754" frameHeight="809"/>
	<SubTexture name="BFRight0010" x="4600" y="676" width="806" height="712" rotated="true" frameX="-0" frameY="-3" frameWidth="754" frameHeight="809"/>
	<SubTexture name="BFRight0011" x="4600" y="676" width="806" height="712" rotated="true" frameX="-0" frameY="-3" frameWidth="754" frameHeight="809"/>
	<SubTexture name="BFRight0012" x="4600" y="676" width="806" height="712" rotated="true" frameX="-0" frameY="-3" frameWidth="754" frameHeight="809"/>
	<SubTexture name="BFRight0013" x="4600" y="676" width="806" height="712" rotated="true" frameX="-0" frameY="-3" frameWidth="754" frameHeight="809"/>
	<SubTexture name="BFRight0014" x="4600" y="676" width="806" height="712" rotated="true" frameX="-0" frameY="-3" frameWidth="754" frameHeight="809"/>
	<SubTexture name="BFRightALT0000" x="6462" y="2173" width="807" height="764" rotated="true" frameX="-26" frameY="-2" frameWidth="790" frameHeight="809"/>
	<SubTexture name="BFRightALT0001" x="0" y="2827" width="771" height="804" frameX="-16" frameY="-5" frameWidth="790" frameHeight="809"/>
	<SubTexture name="BFRightALT0002" x="0" y="2827" width="771" height="804" frameX="-16" frameY="-5" frameWidth="790" frameHeight="809"/>
	<SubTexture name="BFRightALT0003" x="2384" y="2118" width="809" height="756" rotated="true" frameX="-0" frameY="-0" frameWidth="790" frameHeight="809"/>
	<SubTexture name="BFRightALT0004" x="2384" y="2118" width="809" height="756" rotated="true" frameX="-0" frameY="-0" frameWidth="790" frameHeight="809"/>
	<SubTexture name="BFRightALT0005" x="4000" y="1388" width="807" height="745" rotated="true" frameX="-4" frameY="-2" frameWidth="790" frameHeight="809"/>
	<SubTexture name="BFRightALT0006" x="4000" y="1388" width="807" height="745" rotated="true" frameX="-4" frameY="-2" frameWidth="790" frameHeight="809"/>
	<SubTexture name="BFRightALT0007" x="4000" y="1388" width="807" height="745" rotated="true" frameX="-4" frameY="-2" frameWidth="790" frameHeight="809"/>
	<SubTexture name="BFRightALT0008" x="1583" y="1367" width="806" height="740" rotated="true" frameX="-8" frameY="-3" frameWidth="790" frameHeight="809"/>
	<SubTexture name="BFRightALT0009" x="1583" y="1367" width="806" height="740" rotated="true" frameX="-8" frameY="-3" frameWidth="790" frameHeight="809"/>
	<SubTexture name="BFRightALT0010" x="1583" y="1367" width="806" height="740" rotated="true" frameX="-8" frameY="-3" frameWidth="790" frameHeight="809"/>
	<SubTexture name="BFRightALT0011" x="1583" y="1367" width="806" height="740" rotated="true" frameX="-8" frameY="-3" frameWidth="790" frameHeight="809"/>
	<SubTexture name="BFRightALT0012" x="1583" y="1367" width="806" height="740" rotated="true" frameX="-8" frameY="-3" frameWidth="790" frameHeight="809"/>
	<SubTexture name="BFRightALT0013" x="1583" y="1367" width="806" height="740" rotated="true" frameX="-8" frameY="-3" frameWidth="790" frameHeight="809"/>
	<SubTexture name="BFRightALT0014" x="1583" y="1367" width="806" height="740" rotated="true" frameX="-8" frameY="-3" frameWidth="790" frameHeight="809"/>
	<SubTexture name="BFUp0000" x="0" y="0" width="871" height="641" rotated="true" frameX="-19" frameY="-5" frameWidth="674" frameHeight="876"/>
	<SubTexture name="BFUp0001" x="871" y="0" width="876" height="648" rotated="true" frameX="-17" frameY="-0" frameWidth="674" frameHeight="876"/>
	<SubTexture name="BFUp0002" x="871" y="0" width="876" height="648" rotated="true" frameX="-17" frameY="-0" frameWidth="674" frameHeight="876"/>
	<SubTexture name="BFUp0003" x="1747" y="0" width="864" height="666" rotated="true" frameX="-8" frameY="-12" frameWidth="674" frameHeight="876"/>
	<SubTexture name="BFUp0004" x="1747" y="0" width="864" height="666" rotated="true" frameX="-8" frameY="-12" frameWidth="674" frameHeight="876"/>
	<SubTexture name="BFUp0005" x="2611" y="0" width="852" height="672" rotated="true" frameX="-1" frameY="-24" frameWidth="674" frameHeight="876"/>
	<SubTexture name="BFUp0006" x="2611" y="0" width="852" height="672" rotated="true" frameX="-1" frameY="-24" frameWidth="674" frameHeight="876"/>
	<SubTexture name="BFUp0007" x="2611" y="0" width="852" height="672" rotated="true" frameX="-1" frameY="-24" frameWidth="674" frameHeight="876"/>
	<SubTexture name="BFUp0008" x="3463" y="0" width="850" height="672" rotated="true" frameX="-0" frameY="-26" frameWidth="674" frameHeight="876"/>
	<SubTexture name="BFUp0009" x="3463" y="0" width="850" height="672" rotated="true" frameX="-0" frameY="-26" frameWidth="674" frameHeight="876"/>
	<SubTexture name="BFUp0010" x="3463" y="0" width="850" height="672" rotated="true" frameX="-0" frameY="-26" frameWidth="674" frameHeight="876"/>
	<SubTexture name="BFUp0011" x="3463" y="0" width="850" height="672" rotated="true" frameX="-0" frameY="-26" frameWidth="674" frameHeight="876"/>
	<SubTexture name="BFUp0012" x="3463" y="0" width="850" height="672" rotated="true" frameX="-0" frameY="-26" frameWidth="674" frameHeight="876"/>
	<SubTexture name="BFUpALT0000" x="7269" y="2178" width="871" height="764" rotated="true" frameX="-0" frameY="-5" frameWidth="778" frameHeight="876"/>
	<SubTexture name="BFUpALT0001" x="5586" y="2149" width="876" height="763" rotated="true" frameX="-6" frameY="-0" frameWidth="778" frameHeight="876"/>
	<SubTexture name="BFUpALT0002" x="5586" y="2149" width="876" height="763" rotated="true" frameX="-6" frameY="-0" frameWidth="778" frameHeight="876"/>
	<SubTexture name="BFUpALT0003" x="6509" y="1426" width="864" height="747" rotated="true" frameX="-31" frameY="-12" frameWidth="778" frameHeight="876"/>
	<SubTexture name="BFUpALT0004" x="6509" y="1426" width="864" height="747" rotated="true" frameX="-31" frameY="-12" frameWidth="778" frameHeight="876"/>
	<SubTexture name="BFUpALT0005" x="4807" y="1395" width="852" height="745" rotated="true" frameX="-32" frameY="-24" frameWidth="778" frameHeight="876"/>
	<SubTexture name="BFUpALT0006" x="4807" y="1395" width="852" height="745" rotated="true" frameX="-32" frameY="-24" frameWidth="778" frameHeight="876"/>
	<SubTexture name="BFUpALT0007" x="4807" y="1395" width="852" height="745" rotated="true" frameX="-32" frameY="-24" frameWidth="778" frameHeight="876"/>
	<SubTexture name="BFUpALT0008" x="5659" y="1403" width="850" height="746" rotated="true" frameX="-30" frameY="-26" frameWidth="778" frameHeight="876"/>
	<SubTexture name="BFUpALT0009" x="5659" y="1403" width="850" height="746" rotated="true" frameX="-30" frameY="-26" frameWidth="778" frameHeight="876"/>
	<SubTexture name="BFUpALT0010" x="5659" y="1403" width="850" height="746" rotated="true" frameX="-30" frameY="-26" frameWidth="778" frameHeight="876"/>
	<SubTexture name="BFUpALT0011" x="5659" y="1403" width="850" height="746" rotated="true" frameX="-30" frameY="-26" frameWidth="778" frameHeight="876"/>
	<SubTexture name="BFUpALT0012" x="5659" y="1403" width="850" height="746" rotated="true" frameX="-30" frameY="-26" frameWidth="778" frameHeight="876"/>
</TextureAtlas>